pytest_sqlalchemy_session/__init__.py
pytest_sqlalchemy_session/fixtures.py
pytest_sqlalchemy_session/plugin.py
pytest_sqlalchemy_session/session.py
pytest_sqlalchemy_session/version.py
pytest_sqlalchemy_session-0.3.4b1.dist-info/LICENSE
pytest_sqlalchemy_session-0.3.4b1.dist-info/METADATA
pytest_sqlalchemy_session-0.3.4b1.dist-info/WHEEL
pytest_sqlalchemy_session-0.3.4b1.dist-info/entry_points.txt
pytest_sqlalchemy_session-0.3.4b1.dist-info/top_level.txt
pytest_sqlalchemy_session-0.3.4b1.dist-info/RECORD
