Metadata-Version: 2.1
Name: pytest-sqlalchemy-session
Version: 0.3.4b1
Summary: A pytest plugin for preserving test isolation that use SQLAlchemy.
Author-email: Stanislav Shkitin <stanislav.shkitin@yandex.ru>
License: MIT
Keywords: pytest,sqlalchemy,transaction
Classifier: Development Status :: 4 - Beta
Classifier: Framework :: Pytest
Classifier: Intended Audience :: Developers
Classifier: Topic :: Software Development :: Testing
Classifier: Programming Language :: Python
Classifier: Programming Language :: Python :: 3
Classifier: Programming Language :: Python :: 3.7
Classifier: Programming Language :: Python :: 3.8
Classifier: Programming Language :: Python :: 3.9
Classifier: Programming Language :: Python :: 3.10
Classifier: Programming Language :: Python :: 3.11
Classifier: Programming Language :: Python :: 3 :: Only
Classifier: Programming Language :: Python :: Implementation :: CPython
Classifier: Programming Language :: Python :: Implementation :: PyPy
Classifier: Operating System :: OS Independent
Classifier: License :: OSI Approved :: MIT License
Requires-Python: >=3.7
License-File: LICENSE
Requires-Dist: pytest (>=7.0)
Requires-Dist: pytest-mock (>=3.10.0)
Requires-Dist: SQLAlchemy (<2.0,>=1.4.48)
Requires-Dist: packaging (>=14.1)
